itk/StructurePreservingColorNormalizationPython.py
itk/_StructurePreservingColorNormalizationPython.pyd
itk/__init_spcn__.py
itk/itkStructurePreservingColorNormalizationFilterPython.py
itk/Configuration/StructurePreservingColorNormalizationConfig.py
itk/Configuration/StructurePreservingColorNormalization_snake_case.py
itk_spcn.libs/.load-order-itk_spcn-0.2.0
itk_spcn.libs/msvcp140.dll
itk_spcn.libs/tbb12.dll
itk_spcn.libs/vcruntime140_1.dll
itk_spcn-0.2.0.dist-info/DELVEWHEEL
itk_spcn-0.2.0.dist-info/LICENSE
itk_spcn-0.2.0.dist-info/METADATA
itk_spcn-0.2.0.dist-info/WHEEL
itk_spcn-0.2.0.dist-info/top_level.txt
itk_spcn-0.2.0.dist-info/RECORD
